alibabacloud_pai_dlc20201203/__init__.py
alibabacloud_pai_dlc20201203/client.py
alibabacloud_pai_dlc20201203/models/__init__.py
alibabacloud_pai_dlc20201203/models/_aimaster_message.py
alibabacloud_pai_dlc20201203/models/_aliyun_accounts.py
alibabacloud_pai_dlc20201203/models/_assign_node_spec.py
alibabacloud_pai_dlc20201203/models/_assume_user_info.py
alibabacloud_pai_dlc20201203/models/_auto_scaling_spec.py
alibabacloud_pai_dlc20201203/models/_autoscaling_metric_spec.py
alibabacloud_pai_dlc20201203/models/_code_source_item.py
alibabacloud_pai_dlc20201203/models/_container_spec.py
alibabacloud_pai_dlc20201203/models/_create_job_request.py
alibabacloud_pai_dlc20201203/models/_create_job_response.py
alibabacloud_pai_dlc20201203/models/_create_job_response_body.py
alibabacloud_pai_dlc20201203/models/_create_tensorboard_request.py
alibabacloud_pai_dlc20201203/models/_create_tensorboard_response.py
alibabacloud_pai_dlc20201203/models/_create_tensorboard_response_body.py
alibabacloud_pai_dlc20201203/models/_credential_config.py
alibabacloud_pai_dlc20201203/models/_credential_config_item.py
alibabacloud_pai_dlc20201203/models/_credential_role.py
alibabacloud_pai_dlc20201203/models/_data_juicer_config.py
alibabacloud_pai_dlc20201203/models/_data_source_item.py
alibabacloud_pai_dlc20201203/models/_debugger_config.py
alibabacloud_pai_dlc20201203/models/_debugger_job.py
alibabacloud_pai_dlc20201203/models/_debugger_job_issue.py
alibabacloud_pai_dlc20201203/models/_debugger_result.py
alibabacloud_pai_dlc20201203/models/_delete_job_response.py
alibabacloud_pai_dlc20201203/models/_delete_job_response_body.py
alibabacloud_pai_dlc20201203/models/_delete_tensorboard_request.py
alibabacloud_pai_dlc20201203/models/_delete_tensorboard_response.py
alibabacloud_pai_dlc20201203/models/_delete_tensorboard_response_body.py
alibabacloud_pai_dlc20201203/models/_ecs_spec.py
alibabacloud_pai_dlc20201203/models/_env_var.py
alibabacloud_pai_dlc20201203/models/_event_info.py
alibabacloud_pai_dlc20201203-1.6.7.dist-info/LICENSE
alibabacloud_pai_dlc20201203-1.6.7.dist-info/METADATA
alibabacloud_pai_dlc20201203-1.6.7.dist-info/WHEEL
alibabacloud_pai_dlc20201203-1.6.7.dist-info/top_level.txt
alibabacloud_pai_dlc20201203-1.6.7.dist-info/RECORD
